arqio_pycatastro-0.3.0.dist-info/licenses/LICENSE
pycatastro/__init__.py
pycatastro/cli.py
pycatastro/client.py
pycatastro/http_client.py
pycatastro/models.py
pycatastro/tipos.py
pycatastro/endpoints/__init__.py
pycatastro/endpoints/callejero.py
pycatastro/endpoints/coordenadas.py
pycatastro/endpoints/detallada.py
arqio_pycatastro-0.3.0.dist-info/METADATA
arqio_pycatastro-0.3.0.dist-info/WHEEL
arqio_pycatastro-0.3.0.dist-info/entry_points.txt
arqio_pycatastro-0.3.0.dist-info/top_level.txt
arqio_pycatastro-0.3.0.dist-info/RECORD
